{
  "$schema": "https://developer.microsoft.com/json-schemas/fabric/item/report/definition/visualContainer/1.6.0/schema.json",
  "name": "cf3368c09c181c220103",
  "position": {
    "x": 94.208,
    "y": 177.152,
    "z": 2000,
    "height": 416.768,
    "width": 1098.752,
    "tabOrder": 2000
  },
  "visual": {
    "visualType": "pivotTable",
    "query": {
      "queryState": {
        "Rows": {
          "projections": [
            {
              "field": {
                "Column": {
                  "Expression": {
                    "SourceRef": {
                      "Entity": "ActivePlayerGamelogsNamesIncluded"
                    }
                  },
                  "Property": "full_name"
                }
              },
              "queryRef": "ActivePlayerGamelogsNamesIncluded.full_name",
              "nativeQueryRef": "Player Name",
              "active": true,
              "displayName": "Player Name"
            }
          ]
        },
        "Values": {
          "projections": [
            {
              "field": {
                "Measure": {
                  "Expression": {
                    "SourceRef": {
                      "Entity": "Table"
                    }
                  },
                  "Property": "Total Points"
                }
              },
              "queryRef": "Table.Total Points",
              "nativeQueryRef": "Total Points"
            }
          ]
        }
      },
      "sortDefinition": {
        "sort": [
          {
            "field": {
              "Measure": {
                "Expression": {
                  "SourceRef": {
                    "Entity": "Table"
                  }
                },
                "Property": "Total Points"
              }
            },
            "direction": "Descending"
          }
        ]
      }
    },
    "objects": {
      "blankRows": [
        {
          "properties": {
            "showBlankRows": {
              "expr": {
                "Literal": {
                  "Value": "false"
                }
              }
            }
          }
        }
      ],
      "columnWidth": [
        {
          "properties": {
            "value": {
              "expr": {
                "Literal": {
                  "Value": "192.864D"
                }
              }
            }
          },
          "selector": {
            "metadata": "ActivePlayerGamelogsNamesIncluded.full_name"
          }
        }
      ],
      "columnHeaders": [
        {
          "properties": {
            "backColor": {
              "solid": {
                "color": {
                  "expr": {
                    "Literal": {
                      "Value": "'#FFFDEA'"
                    }
                  }
                }
              }
            }
          }
        }
      ],
      "subTotals": [
        {
          "properties": {
            "columnSubtotals": {
              "expr": {
                "Literal": {
                  "Value": "true"
                }
              }
            },
            "rowSubtotals": {
              "expr": {
                "Literal": {
                  "Value": "false"
                }
              }
            }
          }
        }
      ],
      "grid": [
        {
          "properties": {
            "gridHorizontal": {
              "expr": {
                "Literal": {
                  "Value": "true"
                }
              }
            },
            "gridHorizontalWeight": {
              "expr": {
                "Literal": {
                  "Value": "6D"
                }
              }
            },
            "gridHorizontalColor": {
              "solid": {
                "color": {
                  "expr": {
                    "ThemeDataColor": {
                      "ColorId": 0,
                      "Percent": 0
                    }
                  }
                }
              }
            }
          }
        }
      ]
    },
    "visualContainerObjects": {
      "stylePreset": [
        {
          "properties": {
            "name": {
              "expr": {
                "Literal": {
                  "Value": "'None'"
                }
              }
            }
          }
        }
      ],
      "title": [
        {
          "properties": {
            "show": {
              "expr": {
                "Literal": {
                  "Value": "false"
                }
              }
            }
          }
        }
      ]
    },
    "drillFilterOtherVisuals": true
  },
  "filterConfig": {
    "filters": [
      {
        "name": "ffc53d03a055600297de",
        "field": {
          "Column": {
            "Expression": {
              "SourceRef": {
                "Entity": "ActivePlayerGamelogsNamesIncluded"
              }
            },
            "Property": "full_name"
          }
        },
        "type": "TopN",
        "filter": {
          "Version": 2,
          "From": [
            {
              "Name": "subquery",
              "Expression": {
                "Subquery": {
                  "Query": {
                    "Version": 2,
                    "From": [
                      {
                        "Name": "a",
                        "Entity": "ActivePlayerGamelogsNamesIncluded",
                        "Type": 0
                      },
                      {
                        "Name": "t",
                        "Entity": "Table",
                        "Type": 0
                      }
                    ],
                    "Select": [
                      {
                        "Column": {
                          "Expression": {
                            "SourceRef": {
                              "Source": "a"
                            }
                          },
                          "Property": "full_name"
                        },
                        "Name": "field"
                      }
                    ],
                    "OrderBy": [
                      {
                        "Direction": 2,
                        "Expression": {
                          "Measure": {
                            "Expression": {
                              "SourceRef": {
                                "Source": "t"
                              }
                            },
                            "Property": "Total Points"
                          }
                        }
                      }
                    ],
                    "Top": 15
                  }
                }
              },
              "Type": 2
            },
            {
              "Name": "a",
              "Entity": "ActivePlayerGamelogsNamesIncluded",
              "Type": 0
            }
          ],
          "Where": [
            {
              "Condition": {
                "In": {
                  "Expressions": [
                    {
                      "Column": {
                        "Expression": {
                          "SourceRef": {
                            "Source": "a"
                          }
                        },
                        "Property": "full_name"
                      }
                    }
                  ],
                  "Table": {
                    "SourceRef": {
                      "Source": "subquery"
                    }
                  }
                }
              }
            }
          ]
        }
      },
      {
        "name": "1bce496576c62deab038",
        "field": {
          "Column": {
            "Expression": {
              "SourceRef": {
                "Entity": "ActivePlayerGamelogsNamesIncluded"
              }
            },
            "Property": "SEASON_ID"
          }
        },
        "type": "Categorical",
        "filter": {
          "Version": 2,
          "From": [
            {
              "Name": "a",
              "Entity": "ActivePlayerGamelogsNamesIncluded",
              "Type": 0
            }
          ],
          "Where": [
            {
              "Condition": {
                "In": {
                  "Expressions": [
                    {
                      "Column": {
                        "Expression": {
                          "SourceRef": {
                            "Source": "a"
                          }
                        },
                        "Property": "SEASON_ID"
                      }
                    }
                  ],
                  "Values": [
                    [
                      {
                        "Literal": {
                          "Value": "22023L"
                        }
                      }
                    ]
                  ]
                }
              }
            }
          ]
        },
        "howCreated": "User"
      }
    ]
  }
}